{
  "games": [
    {
      "id": 1,
      "away": "CLE",
      "home": "ORL",
      "aS": 122,
      "hS": 128,
      "status": "final",
      "q": "Final",
      "aR": "40-26",
      "hR": "36-28",
      "spread": "",
      "game_date": "2026-03-11"
    },
    {
      "id": 2,
      "away": "TOR",
      "home": "NOP",
      "aS": 111,
      "hS": 122,
      "status": "final",
      "q": "Final",
      "aR": "36-29",
      "hR": "22-45",
      "spread": "",
      "game_date": "2026-03-11"
    },
    {
      "id": 3,
      "away": "NYK",
      "home": "UTA",
      "aS": 134,
      "hS": 117,
      "status": "final",
      "q": "Final",
      "aR": "42-25",
      "hR": "20-46",
      "spread": "",
      "game_date": "2026-03-11"
    },
    {
      "id": 4,
      "away": "HOU",
      "home": "DEN",
      "aS": 93,
      "hS": 129,
      "status": "final",
      "q": "Final",
      "aR": "40-25",
      "hR": "40-26",
      "spread": "",
      "game_date": "2026-03-11"
    },
    {
      "id": 5,
      "away": "CHA",
      "home": "SAC",
      "aS": 117,
      "hS": 109,
      "status": "final",
      "q": "Final",
      "aR": "34-33",
      "hR": "16-51",
      "spread": "",
      "game_date": "2026-03-11"
    },
    {
      "id": 6,
      "away": "MIN",
      "home": "LAC",
      "aS": 128,
      "hS": 153,
      "status": "final",
      "q": "Final",
      "aR": "40-26",
      "hR": "33-32",
      "spread": "",
      "game_date": "2026-03-11"
    }
  ],
  "exported_at": "2026-03-12T06:45:21.872523+00:00"
}