[{"home_team":"DET","away_team":"MEM","game_date":"2026-03-13","model_total":244.7,"book_total":null,"edge":null,"recommendation":null,"value":false,"home_avg_scored":114.9,"away_avg_allowed":123.0,"away_avg_scored":118.3,"home_avg_allowed":111.3,"home_pace_roll10":102.1,"away_pace_roll10":102.6},{"home_team":"IND","away_team":"NYK","game_date":"2026-03-13","model_total":216.1,"book_total":null,"edge":null,"recommendation":null,"value":false,"home_avg_scored":112.6,"away_avg_allowed":103.8,"away_avg_scored":111.6,"home_avg_allowed":127.3,"home_pace_roll10":100.1,"away_pace_roll10":98.6},{"home_team":"TOR","away_team":"PHX","game_date":"2026-03-13","model_total":222.2,"book_total":null,"edge":null,"recommendation":null,"value":false,"home_avg_scored":109.8,"away_avg_allowed":106.7,"away_avg_scored":105.3,"home_avg_allowed":109.0,"home_pace_roll10":100.7,"away_pace_roll10":103.5},{"home_team":"DAL","away_team":"CLE","game_date":"2026-03-13","model_total":219.4,"book_total":null,"edge":null,"recommendation":null,"value":false,"home_avg_scored":107.8,"away_avg_allowed":107.3,"away_avg_scored":111.9,"home_avg_allowed":119.6,"home_pace_roll10":101.0,"away_pace_roll10":102.0},{"home_team":"HOU","away_team":"NOP","game_date":"2026-03-13","model_total":237.7,"book_total":null,"edge":null,"recommendation":null,"value":false,"home_avg_scored":115.2,"away_avg_allowed":118.8,"away_avg_scored":120.6,"home_avg_allowed":110.9,"home_pace_roll10":98.2,"away_pace_roll10":104.0},{"home_team":"GSW","away_team":"MIN","game_date":"2026-03-13","model_total":230.3,"book_total":null,"edge":null,"recommendation":null,"value":false,"home_avg_scored":112.3,"away_avg_allowed":112.8,"away_avg_scored":112.8,"home_avg_allowed":116.8,"home_pace_roll10":100.9,"away_pace_roll10":102.7},{"home_team":"POR","away_team":"UTA","game_date":"2026-03-13","model_total":243.6,"book_total":null,"edge":null,"recommendation":null,"value":false,"home_avg_scored":111.8,"away_avg_allowed":120.2,"away_avg_scored":112.8,"home_avg_allowed":116.4,"home_pace_roll10":103.0,"away_pace_roll10":106.0},{"home_team":"LAC","away_team":"CHI","game_date":"2026-03-13","model_total":241.7,"book_total":null,"edge":null,"recommendation":null,"value":false,"home_avg_scored":117.6,"away_avg_allowed":115.9,"away_avg_scored":109.4,"home_avg_allowed":112.3,"home_pace_roll10":100.8,"away_pace_roll10":105.2}]